py_templatify-0.3.2.dist-info/METADATA
py_templatify-0.3.2.dist-info/WHEEL
py_templatify-0.3.2.dist-info/entry_points.txt
py_templatify-0.3.2.dist-info/licenses/LICENSE
py_templatify/__init__.py
py_templatify/_decorators.py
py_templatify/_shortcuts/__init__.py
py_templatify/_shortcuts/_types.py
py_templatify/_tags/__init__.py
py_templatify/_tags/_base.py
py_templatify/_tags/_markdown.py
py_templatify/_tags/_types.py
py_templatify/_types.py
py_templatify/markdown/__init__.py
py_templatify/markdown/shortcuts.py
py_templatify/markdown/tags.py
py_templatify/py.typed
py_templatify-0.3.2.dist-info/RECORD
