Metadata-Version: 2.4
Name: py-templatify
Version: 0.3.2
Summary: Minimalist Python template generation with type-safe annotations. Perfect for chat bots and LLM prompts.
Author-Email: Galtozzy <galtozzy+git@gmail.com>
License-Expression: MIT
Classifier: Development Status :: 4 - Beta
Classifier: Intended Audience :: Information Technology
Classifier: Intended Audience :: System Administrators
Classifier: Intended Audience :: Developers
Classifier: Operating System :: OS Independent
Classifier: Programming Language :: Python :: 3
Classifier: Programming Language :: Python
Classifier: Typing :: Typed
Classifier: Programming Language :: Python :: 3.13
Classifier: Topic :: Internet :: WWW/HTTP :: Dynamic Content
Project-URL: Homepage, https://github.com/EzyGang/py-templatify
Project-URL: Repository, https://github.com/EzyGang/py-templatify
Requires-Python: <4,>=3.13
Requires-Dist: typing-extensions>=4.12.2; python_full_version < "3.13"
